nfdi/__init__.py
nfdi/data.py
nfdi/info.py
nfdi/nel.py
NFDI-0.1.1.dist-info/LICENSE
NFDI-0.1.1.dist-info/METADATA
NFDI-0.1.1.dist-info/WHEEL
NFDI-0.1.1.dist-info/top_level.txt
NFDI-0.1.1.dist-info/RECORD
