Metadata-Version: 2.1
Name: NFDI
Version: 0.1.1
Summary: Basic info about NFDI consortia. Named entity linking for them. Support for Wikidata WikiProject NFDI.
Home-page: https://github.com/UB-Mannheim/NFDI
Author: Renat Shigapov
License: MIT
Platform: UNKNOWN
Classifier: License :: OSI Approved :: MIT License
Classifier: Intended Audience :: Developers
Classifier: Intended Audience :: Education
Classifier: Intended Audience :: Science/Research
Classifier: Operating System :: OS Independent
Classifier: Programming Language :: Python :: 3.7
Classifier: Programming Language :: Python :: 3.8
Classifier: Programming Language :: Python :: 3.9
Classifier: Topic :: Software Development :: Libraries
Classifier: Topic :: Software Development :: Libraries :: Python Modules
Requires-Python: >=3.7
License-File: LICENSE
Requires-Dist: requests (>=2.24.0)
Requires-Dist: spacy (>=3.1.3)
